gravityspawner/__init__.py
gravityspawner/gravityspawner.py
gravityspawner-0.0.2.dist-info/LICENSE
gravityspawner-0.0.2.dist-info/METADATA
gravityspawner-0.0.2.dist-info/WHEEL
gravityspawner-0.0.2.dist-info/top_level.txt
gravityspawner-0.0.2.dist-info/RECORD
