Metadata-Version: 2.1
Name: gravityspawner
Version: 0.0.2
Summary: GravitySpawner: A spawner for Jupyterhub to let user select and input options at the same time
Home-page: https://github.com/lalalabox/gravityspawner
Author: LALALA
Author-email: toorxkh@gmail.com
License: BSD
Project-URL: Bug Tracker, https://github.com/lalalabox/gravityspawner/issues
Platform: Linux
Platform: Mac OS X
Classifier: Intended Audience :: Developers
Classifier: Intended Audience :: System Administrators
Classifier: Intended Audience :: Science/Research
Classifier: License :: OSI Approved :: BSD License
Classifier: Programming Language :: Python
Classifier: Programming Language :: Python :: 3
Requires-Python: >=3.7
License-File: LICENSE
